pegasusio/__init__.py
pegasusio/__main__.py
pegasusio/aggr_data.py
pegasusio/citeseq_data.py
pegasusio/cyto_data.py
pegasusio/cyto_utils.py
pegasusio/data_aggregation.py
pegasusio/datadict.py
pegasusio/decorators.py
pegasusio/hdf5_utils.py
pegasusio/multimodal_data.py
pegasusio/nanostring_data.py
pegasusio/nanostring_utils.py
pegasusio/qc_utils.py
pegasusio/readwrite.py
pegasusio/spatial_data.py
pegasusio/spatial_utils.py
pegasusio/text_utils.py
pegasusio/unimodal_data.py
pegasusio/vdj_data.py
pegasusio/vdj_utils.py
pegasusio/version.py
pegasusio/views.py
pegasusio/zarr_utils.py
pegasusio/commands/AggregateMatrix.py
pegasusio/commands/Base.py
pegasusio/commands/__init__.py
pegasusio/cylib/funcs.cpython-39-darwin.so
pegasusio/cylib/io.cpython-39-darwin.so
pegasusio-0.10.0.dist-info/licenses/LICENSE
pegasusio-0.10.0.dist-info/METADATA
pegasusio-0.10.0.dist-info/WHEEL
pegasusio-0.10.0.dist-info/entry_points.txt
pegasusio-0.10.0.dist-info/top_level.txt
pegasusio-0.10.0.dist-info/RECORD
