Metadata-Version: 2.4
Name: pegasusio
Version: 0.10.0
Summary: Pegasusio is a Python package for reading / writing single-cell genomics data
Home-page: https://github.com/lilab-bcb/pegasusio
Author: Yiming Yang, Rimte Rocher, Joshua Gould and Bo Li
Author-email: cumulus-support@googlegroups.com
Keywords: single cell/nucleus genomics data reading and writing
Classifier: Development Status :: 4 - Beta
Classifier: Framework :: Jupyter
Classifier: Intended Audience :: Developers
Classifier: Intended Audience :: Science/Research
Classifier: License :: OSI Approved :: BSD License
Classifier: Natural Language :: English
Classifier: Operating System :: MacOS :: MacOS X
Classifier: Operating System :: POSIX :: Linux
Classifier: Programming Language :: Python :: 3
Classifier: Programming Language :: Python :: 3.9
Classifier: Programming Language :: Python :: 3.10
Classifier: Programming Language :: Python :: 3.11
Classifier: Programming Language :: Python :: 3.12
Classifier: Topic :: Software Development :: Build Tools
Classifier: Topic :: Scientific/Engineering :: Bio-Informatics
Requires-Python: ~=3.8
License-File: LICENSE
Requires-Dist: Cython
Requires-Dist: loompy
Requires-Dist: h5py>=3.0.0
Requires-Dist: docopt
Requires-Dist: natsort
Requires-Dist: numpy>=2.0.0
Requires-Dist: pandas>=1.2.0
Requires-Dist: scipy
Requires-Dist: setuptools
Requires-Dist: zarr<=2.18.7
Requires-Dist: Pillow
Dynamic: author
Dynamic: author-email
Dynamic: classifier
Dynamic: description
Dynamic: home-page
Dynamic: keywords
Dynamic: license-file
Dynamic: requires-dist
Dynamic: requires-python
Dynamic: summary
